Workbook

Sheet Dashboard
B2: BASEL II CREDIT RISK MODEL
B3: Expected Loss · Unexpected Loss · Regulatory Capital Calculator
B6: MODEL NAVIGATION
B7: 1. Assumptions | C7: All input parameters — PD, LGD, EAD, Basel risk weights. START HERE.
B8: 2. Loan Book | C8: 15-loan portfolio with individual EL, UL and capital calculations.
B9: 3. Scenario Analysis | C9: Normal vs Recession vs Severe Stress scenario comparison.
B10: 4. Summary | C10: Aggregated portfolio metrics, capital ratios and key risk indicators.
B12: COLOUR CODING CONVENTION (Industry Standard)
B13: Blue text | C13: Hardcoded inputs — values YOU can change
B14: Black text | C14: Formulas & calculated values — do not edit
B15: Green text | C15: Cross-sheet links pulling from another tab
B16: Yellow bg | C16: Key assumption cells requiring attention
B18: BASEL II FRAMEWORK — KEY CONCEPTS
B19: Expected Loss (EL) | C19: EL = PD × LGD × EAD — The average loss a bank expects on a loan/portfolio.
B20: Unexpected Loss (UL) | C20: UL = EAD × LGD × √(PD × (1-PD)) — The volatility around the expected loss.
B21: Regulatory Capital (RC) | C21: RC = Risk-Weighted Assets × 8% (Minimum Capital Adequacy Ratio under Basel II)
B22: PD — Prob. of Default | C22: Probability that a borrower will default within a 1-year horizon.
B23: LGD — Loss Given Default | C23: Fraction of exposure lost if the borrower defaults. (1 - Recovery Rate)
B24: EAD — Exposure at Default | C24: Outstanding loan balance at the time of default.
B25: Risk Weight (RW) | C25: Basel II standard weights: Corporate 100%, Retail 75%, Mortgage 35%, Sovereign 0%

Sheet Assumptions
B2: MODEL ASSUMPTIONS & PARAMETERS
B5: A. PROBABILITY OF DEFAULT (PD) BY CREDIT RATING
B6: Rating Grade | C6: Rating Label | D6: Basel II PD (%) | E6: S&P Equivalent | F6: Description | G6: Source
B7: AAA | C7: Investment Grade — Prime | D7: 0.0001 | E7: AAA | F7: Highest quality, near-zero default risk | G7: Source: GARP FRM Part II / Basel II IRB Guidelines
B8: AA | C8: Investment Grade — High | D8: 0.0005 | E8: AA | F8: Very high quality, minimal risk | G8: Source: GARP FRM Part II / Basel II IRB Guidelines
B9: A | C9: Investment Grade — Upper-Mid | D9: 0.001 | E9: A | F9: Strong capacity to meet obligations | G9: Source: GARP FRM Part II / Basel II IRB Guidelines
B10: BBB | C10: Investment Grade — Lower-Mid | D10: 0.0025 | E10: BBB | F10: Adequate capacity, somewhat exposed | G10: Source: GARP FRM Part II / Basel II IRB Guidelines
B11: BB | C11: Speculative Grade — Upper | D11: 0.01 | E11: BB | F11: Less vulnerable, faces major uncertainties | G11: Source: GARP FRM Part II / Basel II IRB Guidelines
B12: B | C12: Speculative Grade — Mid | D12: 0.03 | E12: B | F12: Vulnerable, currently able to meet obligations | G12: Source: GARP FRM Part II / Basel II IRB Guidelines
B13: CCC | C13: Speculative Grade — Lower | D13: 0.08 | E13: CCC | F13: Currently vulnerable to nonpayment | G13: Source: GARP FRM Part II / Basel II IRB Guidelines
B14: D | C14: Default | D14: 0.2 | E14: D | F14: In default or breach of obligation | G14: Source: GARP FRM Part II / Basel II IRB Guidelines
B16: B. LOSS GIVEN DEFAULT (LGD) BY ASSET CLASS
B17: Asset Class | C17: LGD (%) | D17: Recovery Rate (%) | E17: Basel II RW (%) | F17: Seniority | G17: Note
B18: Senior Secured Loan | C18: 0.4 | D18: =1-C18 -> 0.6 | E18: 1 | F18: Senior Secured | G18: Standard corporate — secured
B19: Senior Unsecured Loan | C19: 0.55 | D19: =1-C19 -> 0.45 | E19: 1 | F19: Senior Unsecured | G19: Standard corporate — unsecured
B20: Subordinated Debt | C20: 0.75 | D20: =1-C20 -> 0.25 | E20: 1 | F20: Subordinated | G20: Higher loss on default
B21: Residential Mortgage | C21: 0.2 | D21: =1-C21 -> 0.8 | E21: 0.35 | F21: Senior Secured | G21: Basel II preferential weight
B22: Retail — Credit Card | C22: 0.65 | D22: =1-C22 -> 0.35 | E22: 0.75 | F22: Unsecured Retail | G22: Revolving retail exposure
B23: Retail — Personal Loan | C23: 0.6 | D23: =1-C23 -> 0.4 | E23: 0.75 | F23: Unsecured Retail | G23: Term retail exposure
B24: Sovereign (India AAA) | C24: 0.05 | D24: =1-C24 -> 0.95 | E24: 0 | F24: Senior | G24: Sovereign preferential weight
B26: C. SCENARIO STRESS MULTIPLIERS (applied in Scenario Analysis sheet)
B27: Scenario | C27: PD Multiplier | D27: LGD Multiplier | E27: Description
B28: Normal (Base Case) | C28: 1 | D28: 1 | E28: Current economic environment — use actual PDs and LGDs
B29: Recession | C29: 2.5 | D29: 1.2 | E29: Moderate downturn; PDs rise 2.5x, LGDs deteriorate 20%
B30: Severe Stress | C30: 5 | D30: 1.4 | E30: Severe financial crisis (e.g. 2008-style); PDs rise 5x
B32: D. CAPITAL ADEQUACY PARAMETERS
B33: Minimum CAR (Basel II) | C33: 0.08 | D33: 8% of Risk-Weighted Assets (Pillar 1 minimum)
B34: Conservation Buffer | C34: 0.025 | D34: Added under Basel III — total 10.5% with Tier 1
B35: Total Required Capital Ratio | C35: =C33+C34 -> 0.105 | D35: Combined minimum under Basel II/III

Sheet Loan Book
B2: LOAN BOOK — INDIVIDUAL LOAN CALCULATIONS
B3: Blue = Input (changeable) | Black = Formula | All monetary values in INR (Lakhs)
B5: # | C5: Borrower Name | D5: Sector | E5: Rating | F5: Asset Class | G5: EAD (₹ Lakhs) | H5: PD (%) | I5: LGD (%) | J5: RW (%) | K5: Expected Loss (₹ Lakhs) | L5: Unexpected Loss (₹ Lakhs) | M5: Risk-Weighted Assets (₹ L) | N5: Reg. Capital Required (₹ L) | O5: EL as % EAD | P5: Capital Adequacy %
B6: 1 | C6: Tata Steel Ltd | D6: Metals & Mining | E6: BBB | F6: Senior Secured Loan | G6: 850 | H6: 0.0025 | I6: 0.4 | J6: 1 | K6: =G6*H6*I6 -> 0.85 | L6: =G6*I6*SQRT(H6*(1-H6)) -> 16.978737 | M6: =G6*J6 -> 850 | N6: =M6*Assumptions!C33 -> 68 | O6: =K6/G6 -> 0.001 | P6: =N6/G6 -> 0.08
B7: 2 | C7: Reliance Retail | D7: Consumer/Retail | E7: A | F7: Senior Unsecured Loan | G7: 1200 | H7: 0.001 | I7: 0.55 | J7: 1 | K7: =G7*H7*I7 -> 0.66 | L7: =G7*I7*SQRT(H7*(1-H7)) -> 20.860594 | M7: =G7*J7 -> 1200 | N7: =M7*Assumptions!C33 -> 96 | O7: =K7/G7 -> 0.00055 | P7: =N7/G7 -> 0.08
B8: 3 | C8: HDFC Home Loans | D8: Mortgage | E8: AA | F8: Residential Mortgage | G8: 2500 | H8: 0.0005 | I8: 0.2 | J8: 0.35 | K8: =G8*H8*I8 -> 0.25 | L8: =G8*I8*SQRT(H8*(1-H8)) -> 11.177544 | M8: =G8*J8 -> 875 | N8: =M8*Assumptions!C33 -> 70 | O8: =K8/G8 -> 0.0001 | P8: =N8/G8 -> 0.028
B9: 4 | C9: IndiGo Airlines | D9: Aviation | E9: BB | F9: Senior Secured Loan | G9: 600 | H9: 0.01 | I9: 0.4 | J9: 1 | K9: =G9*H9*I9 -> 2.4 | L9: =G9*I9*SQRT(H9*(1-H9)) -> 23.879698 | M9: =G9*J9 -> 600 | N9: =M9*Assumptions!C33 -> 48 | O9: =K9/G9 -> 0.004 | P9: =N9/G9 -> 0.08
B10: 5 | C10: Ramesh Sharma | D10: Retail | E10: BBB | F10: Retail — Personal Loan | G10: 15 | H10: 0.0025 | I10: 0.6 | J10: 0.75 | K10: =G10*H10*I10 -> 0.0225 | L10: =G10*I10*SQRT(H10*(1-H10)) -> 0.44943715 | M10: =G10*J10 -> 11.25 | N10: =M10*Assumptions!C33 -> 0.9 | O10: =K10/G10 -> 0.0015 | P10: =N10/G10 -> 0.06
B11: 6 | C11: Priya Kapoor | D11: Retail | E11: A | F11: Retail — Credit Card | G11: 8 | H11: 0.001 | I11: 0.65 | J11: 0.75 | K11: =G11*H11*I11 -> 0.0052 | L11: =G11*I11*SQRT(H11*(1-H11)) -> 0.1643562 | M11: =G11*J11 -> 6 | N11: =M11*Assumptions!C33 -> 0.48 | O11: =K11/G11 -> 0.00065 | P11: =N11/G11 -> 0.06
B12: 7 | C12: Adani Ports | D12: Infrastructure | E12: A | F12: Senior Secured Loan | G12: 950 | H12: 0.001 | I12: 0.4 | J12: 1 | K12: =G12*H12*I12 -> 0.38 | L12: =G12*I12*SQRT(H12*(1-H12)) -> 12.010645 | M12: =G12*J12 -> 950 | N12: =M12*Assumptions!C33 -> 76 | O12: =K12/G12 -> 0.0004 | P12: =N12/G12 -> 0.08
B13: 8 | C13: Yes Bank Ltd | D13: Banking (NBFC) | E13: B | F13: Subordinated Debt | G13: 400 | H13: 0.03 | I13: 0.75 | J13: 1 | K13: =G13*H13*I13 -> 9 | L13: =G13*I13*SQRT(H13*(1-H13)) -> 51.176166 | M13: =G13*J13 -> 400 | N13: =M13*Assumptions!C33 -> 32 | O13: =K13/G13 -> 0.0225 | P13: =N13/G13 -> 0.08
B14: 9 | C14: Govt of India Bond | D14: Sovereign | E14: AAA | F14: Sovereign (India AAA) | G14: 3000 | H14: 0.0001 | I14: 0.05 | J14: 0 | K14: =G14*H14*I14 -> 0.015 | L14: =G14*I14*SQRT(H14*(1-H14)) -> 1.499925 | M14: =G14*J14 -> 0 | N14: =M14*Assumptions!C33 -> 0 | O14: =K14/G14 -> 5e-06 | P14: =N14/G14 -> 0
B15: 10 | C15: Vedanta Resources | D15: Metals & Mining | E15: B | F15: Senior Unsecured Loan | G15: 350 | H15: 0.03 | I15: 0.55 | J15: 1 | K15: =G15*H15*I15 -> 5.775 | L15: =G15*I15*SQRT(H15*(1-H15)) -> 32.83804 | M15: =G15*J15 -> 350 | N15: =M15*Assumptions!C33 -> 28 | O15: =K15/G15 -> 0.0165 | P15: =N15/G15 -> 0.08
B16: 11 | C16: Godrej Properties | D16: Real Estate | E16: BBB | F16: Residential Mortgage | G16: 800 | H16: 0.0025 | I16: 0.2 | J16: 0.35 | K16: =G16*H16*I16 -> 0.4 | L16: =G16*I16*SQRT(H16*(1-H16)) -> 7.9899937 | M16: =G16*J16 -> 280 | N16: =M16*Assumptions!C33 -> 22.4 | O16: =K16/G16 -> 0.0005 | P16: =N16/G16 -> 0.028
B17: 12 | C17: Zomato Ltd | D17: Technology/Food | E17: BB | F17: Senior Unsecured Loan | G17: 250 | H17: 0.01 | I17: 0.55 | J17: 1 | K17: =G17*H17*I17 -> 1.375 | L17: =G17*I17*SQRT(H17*(1-H17)) -> 13.681077 | M17: =G17*J17 -> 250 | N17: =M17*Assumptions!C33 -> 20 | O17: =K17/G17 -> 0.0055 | P17: =N17/G17 -> 0.08
B18: 13 | C18: Kotak Mahindra Bank | D18: Banking | E18: AA | F18: Senior Secured Loan | G18: 1800 | H18: 0.0005 | I18: 0.35 | J18: 1 | K18: =G18*H18*I18 -> 0.315 | L18: =G18*I18*SQRT(H18*(1-H18)) -> 14.083706 | M18: =G18*J18 -> 1800 | N18: =M18*Assumptions!C33 -> 144 | O18: =K18/G18 -> 0.000175 | P18: =N18/G18 -> 0.08
B19: 14 | C19: Rahul Verma | D19: Retail | E19: BB | F19: Retail — Credit Card | G19: 12 | H19: 0.01 | I19: 0.65 | J19: 0.75 | K19: =G19*H19*I19 -> 0.078 | L19: =G19*I19*SQRT(H19*(1-H19)) -> 0.7760902 | M19: =G19*J19 -> 9 | N19: =M19*Assumptions!C33 -> 0.72 | O19: =K19/G19 -> 0.0065 | P19: =N19/G19 -> 0.06
B20: 15 | C20: ONGC Ltd | D20: Energy/PSU | E20: AAA | F20: Sovereign (India AAA) | G20: 2200 | H20: 0.0001 | I20: 0.05 | J20: 0 | K20: =G20*H20*I20 -> 0.011 | L20: =G20*I20*SQRT(H20*(1-H20)) -> 1.099945 | M20: =G20*J20 -> 0 | N20: =M20*Assumptions!C33 -> 0 | O20: =K20/G20 -> 5e-06 | P20: =N20/G20 -> 0
B21: PORTFOLIO TOTALS | G21: =SUM(G6:G20) -> 14935 | K21: =SUM(K6:K20) -> 21.5367 | L21: =SUM(L6:L20) -> 208.66596 | M21: =SUM(M6:M20) -> 7581.25 | N21: =SUM(N6:N20) -> 606.5 | O21: =K21/G21 -> 0.0014420288 | P21: =N21/G21 -> 0.040609307

Sheet Scenario Analysis
B2: SCENARIO ANALYSIS — STRESS TESTING
B3: Applies PD & LGD multipliers from Assumptions sheet | Compares Normal vs Recession vs Severe Stress
B5: # | C5: Borrower | D5: Rating | E5: EAD (₹ L) | F5: Normal EL | G5: Normal Cap. | H5: Recession EL | I5: Recession Cap. | J5: Severe EL | K5: Severe Cap. | L5: EL Increase (Normal→Severe)
B6: 1 | C6: Tata Steel Ltd | D6: BBB | E6: ='Loan Book'!G6 -> 850 | F6: ='Loan Book'!G6*MIN('Loan Book'!H6*Assumptions!$C$28,1)*MIN('Loan Book'!I6*Assumptions!$D$28,1) -> 0.85 | G6: ='Loan Book'!G6*'Loan Book'!J6*Assumptions!$C$33 -> 68 | H6: ='Loan Book'!G6*MIN('Loan Book'!H6*Assumptions!$C$29,1)*MIN('Loan Book'!I6*Assumptions!$D$29,1) -> 2.55 | I6: ='Loan Book'!G6*'Loan Book'!J6*Assumptions!$C$33 -> 68 | J6: ='Loan Book'!G6*MIN('Loan Book'!H6*Assumptions!$C$30,1)*MIN('Loan Book'!I6*Assumptions!$D$30,1) -> 5.95 | K6: ='Loan Book'!G6*'Loan Book'!J6*Assumptions!$C$33 -> 68 | L6: =J6-F6 -> 5.1
B7: 2 | C7: Reliance Retail | D7: A | E7: ='Loan Book'!G7 -> 1200 | F7: ='Loan Book'!G7*MIN('Loan Book'!H7*Assumptions!$C$28,1)*MIN('Loan Book'!I7*Assumptions!$D$28,1) -> 0.66 | G7: ='Loan Book'!G7*'Loan Book'!J7*Assumptions!$C$33 -> 96 | H7: ='Loan Book'!G7*MIN('Loan Book'!H7*Assumptions!$C$29,1)*MIN('Loan Book'!I7*Assumptions!$D$29,1) -> 1.98 | I7: ='Loan Book'!G7*'Loan Book'!J7*Assumptions!$C$33 -> 96 | J7: ='Loan Book'!G7*MIN('Loan Book'!H7*Assumptions!$C$30,1)*MIN('Loan Book'!I7*Assumptions!$D$30,1) -> 4.62 | K7: ='Loan Book'!G7*'Loan Book'!J7*Assumptions!$C$33 -> 96 | L7: =J7-F7 -> 3.96
B8: 3 | C8: HDFC Home Loans | D8: AA | E8: ='Loan Book'!G8 -> 2500 | F8: ='Loan Book'!G8*MIN('Loan Book'!H8*Assumptions!$C$28,1)*MIN('Loan Book'!I8*Assumptions!$D$28,1) -> 0.25 | G8: ='Loan Book'!G8*'Loan Book'!J8*Assumptions!$C$33 -> 70 | H8: ='Loan Book'!G8*MIN('Loan Book'!H8*Assumptions!$C$29,1)*MIN('Loan Book'!I8*Assumptions!$D$29,1) -> 0.75 | I8: ='Loan Book'!G8*'Loan Book'!J8*Assumptions!$C$33 -> 70 | J8: ='Loan Book'!G8*MIN('Loan Book'!H8*Assumptions!$C$30,1)*MIN('Loan Book'!I8*Assumptions!$D$30,1) -> 1.75 | K8: ='Loan Book'!G8*'Loan Book'!J8*Assumptions!$C$33 -> 70 | L8: =J8-F8 -> 1.5
B9: 4 | C9: IndiGo Airlines | D9: BB | E9: ='Loan Book'!G9 -> 600 | F9: ='Loan Book'!G9*MIN('Loan Book'!H9*Assumptions!$C$28,1)*MIN('Loan Book'!I9*Assumptions!$D$28,1) -> 2.4 | G9: ='Loan Book'!G9*'Loan Book'!J9*Assumptions!$C$33 -> 48 | H9: ='Loan Book'!G9*MIN('Loan Book'!H9*Assumptions!$C$29,1)*MIN('Loan Book'!I9*Assumptions!$D$29,1) -> 7.2 | I9: ='Loan Book'!G9*'Loan Book'!J9*Assumptions!$C$33 -> 48 | J9: ='Loan Book'!G9*MIN('Loan Book'!H9*Assumptions!$C$30,1)*MIN('Loan Book'!I9*Assumptions!$D$30,1) -> 16.8 | K9: ='Loan Book'!G9*'Loan Book'!J9*Assumptions!$C$33 -> 48 | L9: =J9-F9 -> 14.4
B10: 5 | C10: Ramesh Sharma | D10: BBB | E10: ='Loan Book'!G10 -> 15 | F10: ='Loan Book'!G10*MIN('Loan Book'!H10*Assumptions!$C$28,1)*MIN('Loan Book'!I10*Assumptions!$D$28,1) -> 0.0225 | G10: ='Loan Book'!G10*'Loan Book'!J10*Assumptions!$C$33 -> 0.9 | H10: ='Loan Book'!G10*MIN('Loan Book'!H10*Assumptions!$C$29,1)*MIN('Loan Book'!I10*Assumptions!$D$29,1) -> 0.0675 | I10: ='Loan Book'!G10*'Loan Book'!J10*Assumptions!$C$33 -> 0.9 | J10: ='Loan Book'!G10*MIN('Loan Book'!H10*Assumptions!$C$30,1)*MIN('Loan Book'!I10*Assumptions!$D$30,1) -> 0.1575 | K10: ='Loan Book'!G10*'Loan Book'!J10*Assumptions!$C$33 -> 0.9 | L10: =J10-F10 -> 0.135
B11: 6 | C11: Priya Kapoor | D11: A | E11: ='Loan Book'!G11 -> 8 | F11: ='Loan Book'!G11*MIN('Loan Book'!H11*Assumptions!$C$28,1)*MIN('Loan Book'!I11*Assumptions!$D$28,1) -> 0.0052 | G11: ='Loan Book'!G11*'Loan Book'!J11*Assumptions!$C$33 -> 0.48 | H11: ='Loan Book'!G11*MIN('Loan Book'!H11*Assumptions!$C$29,1)*MIN('Loan Book'!I11*Assumptions!$D$29,1) -> 0.0156 | I11: ='Loan Book'!G11*'Loan Book'!J11*Assumptions!$C$33 -> 0.48 | J11: ='Loan Book'!G11*MIN('Loan Book'!H11*Assumptions!$C$30,1)*MIN('Loan Book'!I11*Assumptions!$D$30,1) -> 0.0364 | K11: ='Loan Book'!G11*'Loan Book'!J11*Assumptions!$C$33 -> 0.48 | L11: =J11-F11 -> 0.0312
B12: 7 | C12: Adani Ports | D12: A | E12: ='Loan Book'!G12 -> 950 | F12: ='Loan Book'!G12*MIN('Loan Book'!H12*Assumptions!$C$28,1)*MIN('Loan Book'!I12*Assumptions!$D$28,1) -> 0.38 | G12: ='Loan Book'!G12*'Loan Book'!J12*Assumptions!$C$33 -> 76 | H12: ='Loan Book'!G12*MIN('Loan Book'!H12*Assumptions!$C$29,1)*MIN('Loan Book'!I12*Assumptions!$D$29,1) -> 1.14 | I12: ='Loan Book'!G12*'Loan Book'!J12*Assumptions!$C$33 -> 76 | J12: ='Loan Book'!G12*MIN('Loan Book'!H12*Assumptions!$C$30,1)*MIN('Loan Book'!I12*Assumptions!$D$30,1) -> 2.66 | K12: ='Loan Book'!G12*'Loan Book'!J12*Assumptions!$C$33 -> 76 | L12: =J12-F12 -> 2.28
B13: 8 | C13: Yes Bank Ltd | D13: B | E13: ='Loan Book'!G13 -> 400 | F13: ='Loan Book'!G13*MIN('Loan Book'!H13*Assumptions!$C$28,1)*MIN('Loan Book'!I13*Assumptions!$D$28,1) -> 9 | G13: ='Loan Book'!G13*'Loan Book'!J13*Assumptions!$C$33 -> 32 | H13: ='Loan Book'!G13*MIN('Loan Book'!H13*Assumptions!$C$29,1)*MIN('Loan Book'!I13*Assumptions!$D$29,1) -> 27 | I13: ='Loan Book'!G13*'Loan Book'!J13*Assumptions!$C$33 -> 32 | J13: ='Loan Book'!G13*MIN('Loan Book'!H13*Assumptions!$C$30,1)*MIN('Loan Book'!I13*Assumptions!$D$30,1) -> 60 | K13: ='Loan Book'!G13*'Loan Book'!J13*Assumptions!$C$33 -> 32 | L13: =J13-F13 -> 51
B14: 9 | C14: Govt of India Bond | D14: AAA | E14: ='Loan Book'!G14 -> 3000 | F14: ='Loan Book'!G14*MIN('Loan Book'!H14*Assumptions!$C$28,1)*MIN('Loan Book'!I14*Assumptions!$D$28,1) -> 0.015 | G14: ='Loan Book'!G14*'Loan Book'!J14*Assumptions!$C$33 -> 0 | H14: ='Loan Book'!G14*MIN('Loan Book'!H14*Assumptions!$C$29,1)*MIN('Loan Book'!I14*Assumptions!$D$29,1) -> 0.045 | I14: ='Loan Book'!G14*'Loan Book'!J14*Assumptions!$C$33 -> 0 | J14: ='Loan Book'!G14*MIN('Loan Book'!H14*Assumptions!$C$30,1)*MIN('Loan Book'!I14*Assumptions!$D$30,1) -> 0.105 | K14: ='Loan Book'!G14*'Loan Book'!J14*Assumptions!$C$33 -> 0 | L14: =J14-F14 -> 0.09
B15: 10 | C15: Vedanta Resources | D15: B | E15: ='Loan Book'!G15 -> 350 | F15: ='Loan Book'!G15*MIN('Loan Book'!H15*Assumptions!$C$28,1)*MIN('Loan Book'!I15*Assumptions!$D$28,1) -> 5.775 | G15: ='Loan Book'!G15*'Loan Book'!J15*Assumptions!$C$33 -> 28 | H15: ='Loan Book'!G15*MIN('Loan Book'!H15*Assumptions!$C$29,1)*MIN('Loan Book'!I15*Assumptions!$D$29,1) -> 17.325 | I15: ='Loan Book'!G15*'Loan Book'!J15*Assumptions!$C$33 -> 28 | J15: ='Loan Book'!G15*MIN('Loan Book'!H15*Assumptions!$C$30,1)*MIN('Loan Book'!I15*Assumptions!$D$30,1) -> 40.425 | K15: ='Loan Book'!G15*'Loan Book'!J15*Assumptions!$C$33 -> 28 | L15: =J15-F15 -> 34.65
B16: 11 | C16: Godrej Properties | D16: BBB | E16: ='Loan Book'!G16 -> 800 | F16: ='Loan Book'!G16*MIN('Loan Book'!H16*Assumptions!$C$28,1)*MIN('Loan Book'!I16*Assumptions!$D$28,1) -> 0.4 | G16: ='Loan Book'!G16*'Loan Book'!J16*Assumptions!$C$33 -> 22.4 | H16: ='Loan Book'!G16*MIN('Loan Book'!H16*Assumptions!$C$29,1)*MIN('Loan Book'!I16*Assumptions!$D$29,1) -> 1.2 | I16: ='Loan Book'!G16*'Loan Book'!J16*Assumptions!$C$33 -> 22.4 | J16: ='Loan Book'!G16*MIN('Loan Book'!H16*Assumptions!$C$30,1)*MIN('Loan Book'!I16*Assumptions!$D$30,1) -> 2.8 | K16: ='Loan Book'!G16*'Loan Book'!J16*Assumptions!$C$33 -> 22.4 | L16: =J16-F16 -> 2.4
B17: 12 | C17: Zomato Ltd | D17: BB | E17: ='Loan Book'!G17 -> 250 | F17: ='Loan Book'!G17*MIN('Loan Book'!H17*Assumptions!$C$28,1)*MIN('Loan Book'!I17*Assumptions!$D$28,1) -> 1.375 | G17: ='Loan Book'!G17*'Loan Book'!J17*Assumptions!$C$33 -> 20 | H17: ='Loan Book'!G17*MIN('Loan Book'!H17*Assumptions!$C$29,1)*MIN('Loan Book'!I17*Assumptions!$D$29,1) -> 4.125 | I17: ='Loan Book'!G17*'Loan Book'!J17*Assumptions!$C$33 -> 20 | J17: ='Loan Book'!G17*MIN('Loan Book'!H17*Assumptions!$C$30,1)*MIN('Loan Book'!I17*Assumptions!$D$30,1) -> 9.625 | K17: ='Loan Book'!G17*'Loan Book'!J17*Assumptions!$C$33 -> 20 | L17: =J17-F17 -> 8.25
... B20: 15 | C20: ONGC Ltd | D20: AAA | E20: ='Loan Book'!G20 -> 2200 | F20: ='Loan Book'!G20*MIN('Loan Book'!H20*Assumptions!$C$28,1)*MIN('Loan Book'!I20*Assumptions!$D$28,1) -> 0.011 | G20: ='Loan Book'!G20*'Loan Book'!J20*Assumptions!$C$33 -> 0 | H20: ='Loan Book'!G20*MIN('Loan Book'!H20*Assumptions!$C$29,1)*MIN('Loan Book'!I20*Assumptions!$D$29,1) -> 0.033 | I20: ='Loan Book'!G20*'Loan Book'!J20*Assumptions!$C$33 -> 0 | J20: ='Loan Book'!G20*MIN('Loan Book'!H20*Assumptions!$C$30,1)*MIN('Loan Book'!I20*Assumptions!$D$30,1) -> 0.077 | K20: ='Loan Book'!G20*'Loan Book'!J20*Assumptions!$C$33 -> 0 | L20: =J20-F20 -> 0.066
B21: PORTFOLIO TOTALS | E21: =SUM(E6:E20) -> 14935 | F21: =SUM(F6:F20) -> 21.5367 | G21: =SUM(G6:G20) -> 606.5 | H21: =SUM(H6:H20) -> 64.6101 | I21: =SUM(I6:I20) -> 606.5 | J21: =SUM(J6:J20) -> 147.7569 | K21: =SUM(K6:K20) -> 606.5 | L21: =SUM(L6:L20) -> 126.2202
B23: SCENARIO SUMMARY — PORTFOLIO LEVEL
B24: Scenario | C24: Total EL (₹ L) | D24: EL as % Portfolio | E24: Total Reg. Capital | F24: Capital Ratio | G24: Stress Colour
B25: Normal | C25: =F21 -> 21.5367 | D25: =C25/E21 -> 0.0014420288 | E25: =G21 -> 606.5 | F25: =D25/E21 -> 9.6553652e-08 | G25: ✓ Base Case
B26: Recession | C26: =H21 -> 64.6101 | D26: =C26/E21 -> 0.0043260864 | E26: =I21 -> 606.5 | F26: =D26/E21 -> 2.8966096e-07 | G26: ⚠ Elevated Stress
B27: Severe Stress | C27: =J21 -> 147.7569 | D27: =C27/E21 -> 0.0098933311 | E27: =K21 -> 606.5 | F27: =D27/E21 -> 6.6242592e-07 | G27: ✗ Severe Stress

Sheet Summary
B2: PORTFOLIO RISK SUMMARY — KEY METRICS
B4: A. PORTFOLIO KEY RISK INDICATORS
B5: Total Portfolio EAD (₹ Lakhs) | C5: ='Loan Book'!G21 -> 14935 | E5: Sum of all outstanding loan balances in the portfolio
B6: Total Expected Loss (₹ Lakhs) | C6: ='Loan Book'!K21 -> 21.5367 | E6: Average loss expected annually; held as provisions
B7: Total Unexpected Loss (₹ Lakhs) | C7: ='Loan Book'!L21 -> 208.66596 | E7: Standard deviation of loss; basis for economic capital
B8: Total Risk-Weighted Assets (₹ L) | C8: ='Loan Book'!M21 -> 7581.25 | E8: EAD weighted by Basel II risk weights by asset class
B9: Total Regulatory Capital (₹ L) | C9: ='Loan Book'!N21 -> 606.5 | E9: Minimum capital buffer required under Basel II Pillar 1
B10: Portfolio EL Rate (EL/EAD) | C10: ='Loan Book'!O21 -> 0.0014420288 | E10: EL / EAD — lower is better; benchmark < 1% for investment grade
B11: Portfolio Capital Ratio | C11: ='Loan Book'!P21 -> 0.040609307 | E11: Reg. Capital / EAD — should exceed 8% CAR minimum
B12: Number of Loans | C12: =COUNTA('Loan Book'!C6:C20) -> 15 | E12: Total active positions in the loan book
B14: B. SCENARIO COMPARISON — EXPECTED LOSS
B15: Scenario | C15: EL (₹ Lakhs) | D15: EL / EAD | E15: Reg. Capital | F15: EL Increase vs Normal | G15: Status
B16: Normal | C16: ='Scenario Analysis'!C25 -> 21.5367 | D16: ='Scenario Analysis'!D25 -> 0.0014420288 | E16: ='Scenario Analysis'!E25 -> 606.5 | F16: — | G16: Base Case
B17: Recession | C17: ='Scenario Analysis'!C26 -> 64.6101 | D17: ='Scenario Analysis'!D26 -> 0.0043260864 | E17: ='Scenario Analysis'!E26 -> 606.5 | F17: =C17-C16 -> 43.0734 | G17: Elevated
B18: Severe Stress | C18: ='Scenario Analysis'!C27 -> 147.7569 | D18: ='Scenario Analysis'!D27 -> 0.0098933311 | E18: ='Scenario Analysis'!E27 -> 606.5 | F18: =C18-C16 -> 126.2202 | G18: Critical
B20: C. REGULATORY INTERPRETATION — BASEL II
B21: Expected Loss Treatment | C21: Under Basel II, EL is typically covered by loan-loss PROVISIONS (P&L charge). The bank is required to hold provisions ≥ EL for IRB portfolios.
B22: Unexpected Loss Treatment | C22: UL is covered by REGULATORY CAPITAL (equity). The minimum Tier 1 + Tier 2 capital must cover RWA × 8% (Pillar 1 requirement).
B23: Risk-Weighted Assets (RWA) | C23: RWA = EAD × Risk Weight. Sovereign (0%), Mortgages (35%), Retail (75%), Corporate (100%). Lower RW = less capital needed.
B24: Capital Adequacy Ratio (CAR) | C24: CAR = Eligible Capital / RWA ≥ 8%. Banks with lower RWA (e.g. mortgage-heavy books) need less absolute capital for same exposure.
B25: Stress Testing Implication | C25: In recession scenario, EL rises ~2.5x. This tests whether current provisions and capital buffers are sufficient under adverse conditions.
